activereader/__init__.py
activereader/base.py
activereader/gpx.py
activereader/tcx.py
activereader/util.py
activereader-0.0.2.dist-info/LICENSE
activereader-0.0.2.dist-info/METADATA
activereader-0.0.2.dist-info/WHEEL
activereader-0.0.2.dist-info/top_level.txt
activereader-0.0.2.dist-info/RECORD
