Metadata-Version: 2.1
Name: activereader
Version: 0.0.2
Summary: Garmin TCX and GPX file readers for running activities.
Home-page: https://github.com/aaron-schroeder/activereader
Author: Aaron Schroeder
Author-email: aaron@trailzealot.com
License: MIT
Project-URL: Documentation, https://activereader.readthedocs.io/en/stable/
Classifier: License :: OSI Approved :: MIT License
Classifier: Intended Audience :: Developers
Classifier: Programming Language :: Python :: 3
Classifier: Programming Language :: Python :: 3.7
License-File: LICENSE
Requires-Dist: lxml (>=4.6.2)
Requires-Dist: python-dateutil (>=2.8.1)
